{
    "dome" : 
      { 
        "data_dir" : "dome",
        "output_ext" : ".out.nc",
        "logfile_ext" : ".config.oe",
        "config_ext"  : ".config",
        "bit_for_bit_vars" : ["velnorm", "thk"]
      },
    "a" : 
      { 
        "data_dir" : "ismip-hom",
        "output_ext": ".out.nc",
        "logfile_ext" : ".config.oe",
        "config_ext"  : ".config",
        "bit_for_bit_vars" : ["velnorm", "thk"]
      },
    "c" : 
      { 
        "data_dir" : "ismip-hom",
        "output_ext": ".out.nc",
        "logfile_ext" : ".config.oe",
        "config_ext"  : ".config",
        "bit_for_bit_vars" : ["velnorm", "thk"]
      },
    "f" : 
      { 
        "data_dir" : "ismip-hom",
        "output_ext": ".out.nc",
        "logfile_ext" : ".config.oe",
        "config_ext"  : ".config",
        "bit_for_bit_vars" : ["velnorm", "thk"]
      },
    "circular" : 
      { 
        "data_dir" : "shelf",
        "output_ext" : ".out.nc",
        "logfile_ext" : ".config.oe",
        "config_ext"  : ".config",
        "bit_for_bit_vars" : ["velnorm", "thk"]
      },
    "confined" : 
      { 
        "data_dir" : "shelf",
        "output_ext" : ".out.nc",
        "logfile_ext" : ".config.oe",
        "config_ext"  : ".config",
        "bit_for_bit_vars" : ["velnorm", "thk"]
      },
    "stream" : 
      { 
        "data_dir" : "stream",
        "output_ext" : ".out.nc",
        "logfile_ext" : ".config.oe",
        "config_ext"  : ".config",
        "bit_for_bit_vars" : ["velnorm", "thk"]
      }
}
